{"saveScene":"Level1","playerPosition":{"x":1.5903069972991944,"y":-4.811166763305664,"z":0.0},"mapBoundary":"L1","inventorySaveData":[{"itemID":"FireCloth_Hat_FireHat","itemQuantity":3,"slotIndex":0},{"itemID":"Note_01","itemQuantity":1,"slotIndex":5},{"itemID":"HPFruit_01","itemQuantity":3,"slotIndex":9}],"hotBarSaveData":[{"itemID":"HPPotion_03","itemQuantity":3,"slotIndex":0},{"itemID":"HPFruit_05","itemQuantity":2,"slotIndex":1}],"shopSaveData":[{"itemID":"HPFruit_05","itemLeftNumber":3},{"itemID":"HPFruit_06","itemLeftNumber":5},{"itemID":"HPFruit_07","itemLeftNumber":5},{"itemID":"HPPotion_03","itemLeftNumber":5},{"itemID":"HPPotion_02","itemLeftNumber":5}],"timeSaveData":{"minData":2.0,"hourData":13.0,"dateData":0},"playerSaveData":{"playerLevelData":1,"availablePointData":3,"playerCurrentDamageData":20.0,"playerWeaponDamageData":3.0,"playerBulletData":3,"playerCoinData":246,"maxExpData":40.0,"currentExpData":0.0,"maxHealthData":120.0,"currentHealthData":120.0,"currentWeaponID":"WP_03","currentHatID":"IceCloth_Hat_IceHat","currentCoatID":"IceCloth_Coat_IceCoat"}}